yama_health_indices/__init__.py
yama_health_indices/yama_health_indices.py
yama_health_indices-0.0.1.dist-info/METADATA
yama_health_indices-0.0.1.dist-info/WHEEL
yama_health_indices-0.0.1.dist-info/RECORD
