Metadata-Version: 2.1
Name: yama-health-indices
Version: 0.0.1
Summary: A Python package to calculate health indices.
Home-page: https://github.com/SoichiroYamane/yama-health-indices
License: MIT
Keywords: health,indices,python
Author: Soichiro Yamane
Author-email: ttt@gmail.com
Requires-Python: >=3.11,<4.0
Classifier: License :: OSI Approved :: MIT License
Classifier: Programming Language :: Python :: 3
Classifier: Programming Language :: Python :: 3.11
Classifier: Programming Language :: Python :: 3.12
Project-URL: Repository, https://github.com/SoichiroYamane/yama-health-indices
